FlywheelGearAudit
