Metadata-Version: 2.1
Name: fw-gear-audit
Version: 0.0.4
Summary: A Python SDK tool for auditing gear run data
Home-page: https://github.com/PennBBL/fw-gear-audit
Author: Tinashe M. Tapera
Author-email: tinashemtapera@gmail.com
License: UNKNOWN
Platform: UNKNOWN
Classifier: Programming Language :: Python :: 3.6
Classifier: License :: OSI Approved :: MIT License
Classifier: Operating System :: OS Independent
